kyrielight/__init__.py
kyrielight-0.0.0a1.dist-info/WHEEL
kyrielight-0.0.0a1.dist-info/METADATA
kyrielight-0.0.0a1.dist-info/RECORD
