Metadata-Version: 2.1
Name: kyrielight
Version: 0.0.0a1
Summary: A WIP app for some random api.
Author: mooncell07
Author-email: mooncell07@users.noreply.github.com
Requires-Python: >=3.7,<4.0
Classifier: Programming Language :: Python :: 3
Classifier: Programming Language :: Python :: 3.10
Classifier: Programming Language :: Python :: 3.7
Classifier: Programming Language :: Python :: 3.8
Classifier: Programming Language :: Python :: 3.9
